torchdevice/__init__.py
torchdevice/cuda.py
torchdevice-0.2.0.dist-info/METADATA
torchdevice-0.2.0.dist-info/WHEEL
torchdevice-0.2.0.dist-info/top_level.txt
torchdevice-0.2.0.dist-info/RECORD
